os_ken/__init__.py
os_ken/cfg.py
os_ken/exception.py
os_ken/flags.py
os_ken/hooks.py
os_ken/log.py
os_ken/utils.py
os_ken/app/__init__.py
os_ken/app/ofctl/__init__.py
os_ken/app/ofctl/api.py
os_ken/app/ofctl/event.py
os_ken/app/ofctl/exception.py
os_ken/app/ofctl/service.py
os_ken/base/__init__.py
os_ken/base/app_manager.py
os_ken/contrib/__init__.py
os_ken/controller/__init__.py
os_ken/controller/conf_switch.py
os_ken/controller/controller.py
os_ken/controller/dpset.py
os_ken/controller/event.py
os_ken/controller/handler.py
os_ken/controller/mac_to_network.py
os_ken/controller/mac_to_port.py
os_ken/controller/network.py
os_ken/controller/ofp_api.py
os_ken/controller/ofp_event.py
os_ken/controller/ofp_handler.py
os_ken/controller/tunnels.py
os_ken/lib/__init__.py
os_ken/lib/addrconv.py
os_ken/lib/alert.py
os_ken/lib/bfdlib.py
os_ken/lib/dpid.py
os_ken/lib/hub.py
os_ken/lib/igmplib.py
os_ken/lib/ip.py
os_ken/lib/lacplib.py
os_ken/lib/mac.py
os_ken/lib/mrtlib.py
os_ken/lib/netdevice.py
os_ken/lib/ofctl_nicira_ext.py
os_ken/lib/ofctl_string.py
os_ken/lib/ofctl_utils.py
os_ken/lib/ofctl_v1_0.py
os_ken/lib/ofctl_v1_2.py
os_ken/lib/ofctl_v1_3.py
os_ken/lib/ofctl_v1_4.py
os_ken/lib/ofctl_v1_5.py
os_ken/lib/ofp_pktinfilter.py
os_ken/lib/pack_utils.py
os_ken/lib/pcaplib.py
os_ken/lib/port_no.py
os_ken/lib/rpc.py
os_ken/lib/snortlib.py
os_ken/lib/sockaddr.py
os_ken/lib/sockopt.py
os_ken/lib/stplib.py
os_ken/lib/stringify.py
os_ken/lib/type_desc.py
os_ken/lib/netconf/__init__.py
os_ken/lib/netconf/constants.py
os_ken/lib/netconf/netconf.xsd
os_ken/lib/netconf/xml.xsd
os_ken/lib/of_config/__init__.py
os_ken/lib/of_config/base.py
os_ken/lib/of_config/capable_switch.py
os_ken/lib/of_config/classes.py
os_ken/lib/of_config/constants.py
os_ken/lib/of_config/generated_classes.py
os_ken/lib/of_config/ietf-inet-types.xsd
os_ken/lib/of_config/ietf-yang-types.xsd
os_ken/lib/of_config/of-config-1.0.xsd
os_ken/lib/of_config/of-config-1.1.1.xsd
os_ken/lib/of_config/of-config-1.1.xsd
os_ken-4.1.0.dist-info/licenses/AUTHORS
os_ken-4.1.0.dist-info/licenses/LICENSE
os_ken-4.1.0.dist-info/METADATA
os_ken-4.1.0.dist-info/WHEEL
os_ken-4.1.0.dist-info/pbr.json
os_ken-4.1.0.dist-info/top_level.txt
os_ken-4.1.0.dist-info/RECORD
