Metadata-Version: 2.4
Name: os-ken
Version: 4.1.0
Summary: A component-based software defined networking framework for OpenStack.
Home-page: http://www.openstack.org/
Author: OpenStack
Author-email: openstack-discuss@lists.openstack.org
Classifier: Environment :: OpenStack
Classifier: Intended Audience :: Information Technology
Classifier: Intended Audience :: System Administrators
Classifier: License :: OSI Approved :: Apache Software License
Classifier: Operating System :: POSIX :: Linux
Classifier: Programming Language :: Python
Classifier: Programming Language :: Python :: 3
Classifier: Programming Language :: Python :: 3.10
Classifier: Programming Language :: Python :: 3.11
Classifier: Programming Language :: Python :: 3.12
Classifier: Programming Language :: Python :: 3.13
Requires-Python: >=3.10
License-File: LICENSE
License-File: AUTHORS
Requires-Dist: pbr>=2.0.0
Requires-Dist: eventlet>=0.27.0
Requires-Dist: msgpack>=1.0.0
Requires-Dist: ncclient>=0.6.13
Requires-Dist: netaddr>=0.7.18
Requires-Dist: oslo.config>=5.1.0
Requires-Dist: ovs>=2.8.0
Requires-Dist: packaging>=20.4
Requires-Dist: Routes>=2.3.1
Requires-Dist: WebOb>=1.8.2
Dynamic: author
Dynamic: author-email
Dynamic: classifier
Dynamic: description
Dynamic: home-page
Dynamic: license-file
Dynamic: requires-dist
Dynamic: requires-python
Dynamic: summary
